skjold/__init__.py
skjold/cli.py
skjold/core.py
skjold/cvss.py
skjold/formats.py
skjold/ignore.py
skjold/sources/__init__.py
skjold/sources/gemnasium.py
skjold/sources/github.py
skjold/sources/osv.py
skjold/sources/pypa.py
skjold/sources/pyup.py
skjold/tasks.py
skjold-0.6.2.dist-info/LICENSE
skjold-0.6.2.dist-info/METADATA
skjold-0.6.2.dist-info/WHEEL
skjold-0.6.2.dist-info/entry_points.txt
skjold-0.6.2.dist-info/RECORD
