Metadata-Version: 2.1
Name: skjold
Version: 0.6.2
Summary: Security audit Python project dependencies against security advisory databases.
Home-page: https://github.com/twu/skjold
License: MIT
Keywords: security,security-vulnerability,vulnerability-scanners,vulnerabilities,vulnerability-detection
Author: Thomas Wurmitzer
Author-email: stdin@twu.codes
Requires-Python: >=3.7,<4.0
Classifier: Development Status :: 4 - Beta
Classifier: Environment :: Console
Classifier: Intended Audience :: Developers
Classifier: License :: OSI Approved :: MIT License
Classifier: Operating System :: OS Independent
Classifier: Programming Language :: Python
Classifier: Programming Language :: Python :: 3
Classifier: Programming Language :: Python :: 3.7
Classifier: Programming Language :: Python :: 3.8
Classifier: Programming Language :: Python :: 3.9
Classifier: Programming Language :: Python :: 3.10
Classifier: Programming Language :: Python :: 3.11
Classifier: Programming Language :: Python :: 3 :: Only
Classifier: Topic :: Security
Classifier: Topic :: Software Development :: Build Tools
Classifier: Topic :: Software Development :: Quality Assurance
Classifier: Topic :: Utilities
Classifier: Typing :: Typed
Requires-Dist: click (>=8,<9)
Requires-Dist: packaging (>=21,<24)
Requires-Dist: pyyaml (>=6.0,<7.0)
Requires-Dist: toml (>=0.10.0)
Project-URL: Bug Tracker, https://github.com/twu/skjold/issues
Project-URL: Changelog, https://github.com/twu/skjold/releases
Project-URL: Repository, https://github.com/twu/skjold
